onthisday/__init__.py
onthisday/__main__.py
onthisday/event.py
onthisday/source.py
onthisday/today.py
onthisday-1.1.0.dist-info/LICENSE
onthisday-1.1.0.dist-info/METADATA
onthisday-1.1.0.dist-info/WHEEL
onthisday-1.1.0.dist-info/top_level.txt
onthisday-1.1.0.dist-info/RECORD
