Metadata-Version: 2.1
Name: onthisday
Version: 1.1.0
Summary: Retrieve events that happened on current day
Home-page: https://github.com/bit97/onthisday
Author: bit97
Author-email: federico.bitondo@gmail.com
License: WTFPL
Download-URL: https://github.com/bit97/onthisday/archive/refs/tags/1.1.0.tar.gz
Keywords: cli,command-line,wikipedia,scraping,today-widget,today,greetings
Platform: UNKNOWN
Classifier: Development Status :: 3 - Alpha
Classifier: Intended Audience :: Developers
Classifier: Topic :: Software Development :: Libraries
Classifier: Topic :: Utilities
Classifier: Environment :: Console
Classifier: Operating System :: OS Independent
Classifier: Programming Language :: Python :: 3
Classifier: Programming Language :: Python :: 3.8
Classifier: Programming Language :: Python :: 3.9
Classifier: Programming Language :: Python :: 3.10
License-File: LICENSE
Requires-Dist: Babel
Requires-Dist: beautifulsoup4
Requires-Dist: typer
